<?xml version="1.0" encoding="UTF-8"?>
<odoo>

    <!-- Remove inline HSN/SAC Code display from l10n_in_sale
         Commented out: l10n_in_sale.gst_report_saleorder_document_inherit does not exist in Odoo 19
    <template id="hide_inline_hsn_sale"
              inherit_id="l10n_in_sale.gst_report_saleorder_document_inherit">
        <xpath expr="//h6/strong[hasclass('ml16')]/.." position="replace"/>
    </template>
    -->

    <!-- Add HSN/SAC as a separate column in sale order report -->
    <template id="sale_hsn_column"
              inherit_id="sale.report_saleorder_document">

        <!-- Add HSN/SAC column header after Description -->
        <xpath expr="//th[@name='th_description']" position="after">
            <th name="th_hsn_sac" class="text-start">HSN/SAC</th>
        </xpath>

        <!-- Add HSN/SAC data cell after Description cell -->
        <xpath expr="//td[@name='td_product_name']" position="after">
            <td name="td_hsn_sac">
                <span t-if="line.product_id.l10n_in_hsn_code"
                      t-field="line.product_id.l10n_in_hsn_code"/>
            </td>
        </xpath>

    </template>

    <!-- Static Payment Milestone block (fixed 40/20/30/10 milestones, with the
         base amount taken from each order's untaxed amount). Rendered just
         before the totals block, matching the proforma layout. -->
    <template id="sale_payment_milestone"
              inherit_id="sale.report_saleorder_document">
        <xpath expr="//div[@name='so_total_summary']" position="before">
            <div name="payment_milestone" style="margin-top:8px; font-style:italic;">
                <div><strong>Payment Milestone:</strong></div>
                <div>1).Advance payment 40% on Rs.<span
                        t-field="doc.amount_untaxed"
                        t-options='{"widget": "float", "precision": 0}'/>/-</div>
                <div>2).Upon BRD Sign off 20% on Rs.<span
                        t-field="doc.amount_untaxed"
                        t-options='{"widget": "float", "precision": 0}'/>/-</div>
                <div>3).After UAT Sign off 30% on Rs.<span
                        t-field="doc.amount_untaxed"
                        t-options='{"widget": "float", "precision": 0}'/>/-</div>
                <div>4).After user onboarding 10% on Rs.<span
                        t-field="doc.amount_untaxed"
                        t-options='{"widget": "float", "precision": 0}'/>/-</div>
            </div>
        </xpath>
    </template>

    <!-- Add Declaration and Authorised Signatory to sale order PDF -->
    <template id="sale_declaration_signatory"
              inherit_id="sale.report_saleorder_document">
        <!-- Keep note in its original position, add declaration+signatory after -->
        <xpath expr="//span[@name='order_note']/.." position="after">
            <table style="width:100%; margin-top:10px; border-collapse:collapse;">
                <tr>
                    <td style="width:45%; vertical-align:top; padding-right:20px;">
                        <strong>Declaration</strong><br/>
                        We declare that this invoice shows the actual price of the goods/<br/>
                        Services described and that all particulars are true and correct
                    </td>
                    <td style="width:55%; vertical-align:top; text-align:center;">

                        <div>
                            for
                            <span t-field="doc.company_id.name"/>
                        </div>

                        <!-- Images -->
                        <div style="height:100px; display:flex; justify-content:center; align-items:center; gap:10px;">

                            <!-- Signature -->
                            <img src="/custom_invoice/static/src/img/sign.png"
                                 style="max-height:80px;"/>

                            <!-- Stamp -->
                            <img src="/custom_invoice/static/src/img/seal.png"
                                 style="max-height:80px;"/>

                        </div>

                        <div>
                            <strong>Authorised Signatory</strong>
                        </div>

                    </td>
                </tr>
            </table>
        </xpath>
    </template>

</odoo>
